fileworker/FileWorkerPy.py
fileworker/__init__.py
TheAlixi_fileworkerpy-0.0.2.dist-info/LICENSE
TheAlixi_fileworkerpy-0.0.2.dist-info/METADATA
TheAlixi_fileworkerpy-0.0.2.dist-info/WHEEL
TheAlixi_fileworkerpy-0.0.2.dist-info/top_level.txt
TheAlixi_fileworkerpy-0.0.2.dist-info/RECORD
