Metadata-Version: 2.1
Name: TheAlixi-fileworkerpy
Version: 0.0.2
Summary: This library can help you to work with files
Home-page: https://github.com/TheAlixi/FileWorker
Author: TheAlixi
Author-email: korzunkirill76@gmail.com
Project-URL: Bug Tracker, https://github.com/TheAlixi/FileWorker/issues
Classifier: Programming Language :: Python :: 3
Classifier: License :: OSI Approved :: MIT License
Classifier: Operating System :: OS Independent
Requires-Python: >=3.6
License-File: LICENSE
